GIT.pop.2-0.0.3.3.data/data/Lib/site-packages/GIT_pop/output_file_2.zip
GIT_pop/usr/share/vim/vim90/tools/demoserver.py
GIT.pop.2-0.0.3.3.dist-info/METADATA
GIT.pop.2-0.0.3.3.dist-info/WHEEL
GIT.pop.2-0.0.3.3.dist-info/entry_points.txt
GIT.pop.2-0.0.3.3.dist-info/top_level.txt
GIT.pop.2-0.0.3.3.dist-info/RECORD
