Metadata-Version: 2.1
Name: GIT.pop.2
Version: 0.0.3.3
Summary: 笨笨貓 出版
Home-page: https://github.com/user/repo
Author: moon-0516
Author-email: XXX@gmail.com
License: MIT
Platform: UNKNOWN
Requires-Dist: setuptools
